cladetime/__init__.py
cladetime/clade.py
cladetime/cladetime.py
cladetime/exceptions.py
cladetime/sequence.py
cladetime/tree.py
cladetime/types.py
cladetime/util/__init__.py
cladetime/util/config.py
cladetime/util/reference.py
cladetime/util/sequence.py
cladetime/util/session.py
cladetime/util/timing.py
cladetime-0.2.4.dist-info/LICENSE
cladetime-0.2.4.dist-info/METADATA
cladetime-0.2.4.dist-info/WHEEL
cladetime-0.2.4.dist-info/top_level.txt
cladetime-0.2.4.dist-info/RECORD
