Metadata-Version: 2.2
Name: cladetime
Version: 0.2.4
Summary: Assign clades to SARS-CoV-2 genome sequences at a point in time.
Author-email: "Reich Lab @ University of Massachusetts" <nick@umass.edu>
Maintainer-email: Becky Sweger <rsweger@umass.edu>, Evan Ray <elray@umass.edu>, Ben Rogers <bwrogers@umass.edu>
License: MIT License
Project-URL: Repository, https://github.com/reichlab/cladetime.git
Project-URL: Documentation, https://cladetime.readthedocs.io/
Project-URL: Issues, https://github.com/reichlab/cladetime/issues
Keywords: biostatistics,clade,covid,epidemiology,genome,sequence
Classifier: Development Status :: 4 - Beta
Classifier: License :: OSI Approved :: MIT License
Classifier: Natural Language :: English
Classifier: Operating System :: OS Independent
Classifier: Programming Language :: Python :: 3
Classifier: Topic :: Scientific/Engineering
Classifier: Topic :: Scientific/Engineering :: Bio-Informatics
Requires-Python: >=3.11
License-File: LICENSE
Requires-Dist: awscli>=1.32.92
Requires-Dist: biopython
Requires-Dist: boto3
Requires-Dist: cloudpathlib
Requires-Dist: docker
Requires-Dist: pandas
Requires-Dist: polars>=1.17.1
Requires-Dist: pyarrow
Requires-Dist: requests>=2.32.0
Requires-Dist: rich
Requires-Dist: structlog
Requires-Dist: tqdm
Requires-Dist: urllib3
Requires-Dist: us
Requires-Dist: zstandard
Provides-Extra: dev
Requires-Dist: boto3-stubs[s3]; extra == "dev"
Requires-Dist: coverage; extra == "dev"
Requires-Dist: freezegun; extra == "dev"
Requires-Dist: jinja2>3.1.4; extra == "dev"
Requires-Dist: moto; extra == "dev"
Requires-Dist: mypy; extra == "dev"
Requires-Dist: pytest; extra == "dev"
Requires-Dist: pytest-mock; extra == "dev"
Requires-Dist: ruff; extra == "dev"
Requires-Dist: types-python-dateutil; extra == "dev"
Requires-Dist: types-requests; extra == "dev"
Provides-Extra: docs
Requires-Dist: furo; extra == "docs"
Requires-Dist: jinja2>3.1.4; extra == "docs"
Requires-Dist: matplotlib; extra == "docs"
Requires-Dist: myst-parser; extra == "docs"
Requires-Dist: sphinx<6.0,>=5.0; extra == "docs"
Requires-Dist: sphinx-autobuild; extra == "docs"
Requires-Dist: sphinx-copybutton; extra == "docs"
Requires-Dist: sphinx-github-style; extra == "docs"
Requires-Dist: sphinxext-opengraph; extra == "docs"
Requires-Dist: sphinx_toolbox; extra == "docs"
